[{"class_name": "Beetles", "bbox": "210 0 277 56", "used": true}, {"class_name": "Beetles", "bbox": "312 125 384 185", "used": true}, {"class_name": "Beetles", "bbox": "205 291 267 341", "used": true}, {"class_name": "Beetles", "bbox": "169 192 224 237", "used": true}, {"class_name": "Beetles", "bbox": "389 446 448 497", "used": true}, {"class_name": "Beetles", "bbox": "122 243 191 305", "used": true}, {"class_name": "Beetles", "bbox": "354 205 422 255", "used": true}, {"class_name": "Beetles", "bbox": "181 98 253 162", "used": true}, {"class_name": "Beetles", "bbox": "243 416 312 471", "used": true}]