[{"class_name": "Beetles", "bbox": "341 314 408 368", "used": true}, {"class_name": "Beetles", "bbox": "125 369 189 421", "used": true}, {"class_name": "Beetles", "bbox": "459 466 508 511", "used": true}, {"class_name": "Beetles", "bbox": "8 423 66 479", "used": true}, {"class_name": "Beetles", "bbox": "351 427 407 475", "used": true}, {"class_name": "Beetles", "bbox": "25 273 85 321", "used": true}, {"class_name": "Beetles", "bbox": "79 305 134 350", "used": true}, {"class_name": "Beetles", "bbox": "462 321 510 368", "used": true}]