[{"class_name": "Beetles", "bbox": "333 317 391 365", "used": true}, {"class_name": "Beetles", "bbox": "130 206 182 255", "used": true}, {"class_name": "Beetles", "bbox": "241 294 310 369", "used": true}, {"class_name": "Beetles", "bbox": "292 60 358 114", "used": true}, {"class_name": "Beetles", "bbox": "39 60 105 108", "used": true}, {"class_name": "Beetles", "bbox": "90 382 144 426", "used": true}, {"class_name": "Beetles", "bbox": "41 275 95 317", "used": true}, {"class_name": "Beetles", "bbox": "201 467 235 502", "used": true}, {"class_name": "Beetles", "bbox": "174 192 219 232", "used": true}]