[{"class_name": "Beetles", "bbox": "262 79 328 139", "used": true}, {"class_name": "Beetles", "bbox": "140 136 222 210", "used": true}, {"class_name": "Beetles", "bbox": "85 378 150 429", "used": true}, {"class_name": "Beetles", "bbox": "296 398 369 454", "used": true}, {"class_name": "Beetles", "bbox": "8 359 68 418", "used": true}, {"class_name": "Beetles", "bbox": "47 263 121 320", "used": true}, {"class_name": "Beetles", "bbox": "298 369 386 447", "used": true}, {"class_name": "Beetles", "bbox": "4 471 40 509", "used": true}, {"class_name": "Beetles", "bbox": "151 482 209 511", "used": true}]