[{"class_name": "Beetles", "bbox": "21 185 98 256", "used": true}, {"class_name": "Beetles", "bbox": "221 301 311 362", "used": true}, {"class_name": "Beetles", "bbox": "369 102 440 173", "used": true}, {"class_name": "Beetles", "bbox": "365 271 398 300", "used": true}, {"class_name": "Beetles", "bbox": "345 76 435 163", "used": true}, {"class_name": "Beetles", "bbox": "216 117 255 146", "used": true}, {"class_name": "Beetles", "bbox": "474 470 509 509", "used": true}, {"class_name": "Beetles", "bbox": "98 233 132 272", "used": true}, {"class_name": "Beetles", "bbox": "343 37 383 83", "used": true}]