[{"class_name": "Beetles", "bbox": "57 240 123 296", "used": true}, {"class_name": "Beetles", "bbox": "58 322 123 376", "used": true}, {"class_name": "Beetles", "bbox": "463 168 511 229", "used": true}, {"class_name": "Beetles", "bbox": "226 246 299 308", "used": true}, {"class_name": "Beetles", "bbox": "217 432 277 481", "used": true}, {"class_name": "Beetles", "bbox": "195 220 265 283", "used": true}, {"class_name": "Beetles", "bbox": "213 0 281 51", "used": true}, {"class_name": "Beetles", "bbox": "364 103 429 156", "used": true}, {"class_name": "Beetles", "bbox": "319 318 378 365", "used": true}, {"class_name": "Beetles", "bbox": "457 11 511 69", "used": true}, {"class_name": "Beetles", "bbox": "2 290 53 339", "used": true}, {"class_name": "Beetles", "bbox": "206 226 287 299", "used": true}, {"class_name": "Beetles", "bbox": "91 156 179 217", "used": true}, {"class_name": "Beetles", "bbox": "72 47 141 103", "used": true}]