[{"class_name": "Beetles", "bbox": "170 38 232 96", "used": true}, {"class_name": "Beetles", "bbox": "422 297 493 362", "used": true}, {"class_name": "Beetles", "bbox": "216 344 278 397", "used": true}, {"class_name": "Beetles", "bbox": "26 189 87 242", "used": true}, {"class_name": "Beetles", "bbox": "456 75 511 134", "used": true}, {"class_name": "Beetles", "bbox": "143 144 224 224", "used": true}, {"class_name": "Beetles", "bbox": "266 286 314 330", "used": true}, {"class_name": "Beetles", "bbox": "303 370 361 420", "used": true}, {"class_name": "Beetles", "bbox": "0 249 27 308", "used": true}]